{
  "title": "Призрачная шестёрка",
  "poster": "",
  "fields": {
    "hero-title": "Призрачная шестёрка",
    "hero-eyebrow": "| NETFLIX ORIGINAL",
    "hero-desc": "Эксцентричный миллиардер инсценирует собственную смерть и собирает команду из шести лучших специалистов со всего мира. Отказавшись от своих прежних личностей, они становятся «призраками» и начинают борьбу с опасными преступниками и диктаторами. Их ждут безумные погони, масштабные операции и рискованные миссии по всему миру.",
    "badge-1": "2019",
    "badge-2": "дубляж",
    "badge-3": "128 мин",
    "badge-4": "720p",
    "imdb-rating": "6.1",
    "genre-1": "БОЕВИК",
    "genre-4": "ПРИКЛЮЧЕНИЯ",
    "genre-2": "ТРИЛЛЕР",
    "genre-3": "КОМЕДИЯ"
  },
  "videoUrl": "",
  "siteName": "Видеоархив 2019",
  "siteTagline": "Призрачная шестёрка",
  "footerText": "© ПРИЗРАЧНАЯ ШЕСТЁРКА • 2019 • NETFLIX",
  "heroBg": {
    "type": "upload",
    "value": "backgrounds/lfzepz9l.jpg"
  },
  "bgPosition": {
    "x": 40.09265858873841,
    "y": 76.9230769230769,
    "scale": 1
  },
  "colors": {
    "title": "#ffffff",
    "accentText": "#22c55e",
    "btn": "#f5c518",
    "shape": "",
    "bgPrimary": "#f5c518",
    "bgSecondary": "#22c55e"
  }
}