{
  "title": "Это всё он",
  "poster": "posters/r5d8wgt3.jpg",
  "fields": {
    "badge-1": "2021",
    "hero-eyebrow": "| NETFLIX ORIGINAL",
    "badge-2": "Дубляж",
    "badge-3": "91 минута",
    "badge-4": "1080p",
    "hero-desc": "Популярная школьная инфлюенсер Пэджет после публичного скандала заключает спор: она должна превратить самого неприметного парня школы в короля выпускного бала. Со временем их история перестаёт быть игрой — между ними возникают настоящие чувства, которые меняют всё.",
    "imdb-rating": "4.4",
    "genre-1": "<br>"
  },
  "videoUrl": "",
  "siteName": "Видеоархив",
  "siteTagline": "—",
  "footerText": "© «ЭТО ВСЁ ОН» • 2021 • NETFLIX",
  "heroBg": {
    "type": "upload",
    "value": "backgrounds/r5d8wgt3.jpg"
  },
  "bgPosition": {
    "x": 45.81043956043956,
    "y": 53.26923076923077,
    "scale": 1
  },
  "colors": {
    "title": "#ffffff",
    "accentText": "#ec4899",
    "btn": "#3b82f6",
    "shape": "#f43f5e",
    "bgPrimary": "#ec4899",
    "bgSecondary": "#3b82f6"
  }
}