{
  "title": "ТАЙЛЕР РЕЙК: ОПЕРАЦИЯ ПО СПАСЕНИЮ 2",
  "poster": "",
  "fields": {
    "hero-title": "ТАЙЛЕР РЕЙК: ОПЕРАЦИЯ ПО СПАСЕНИЮ 2",
    "hero-eyebrow": "| NETFLIX ORIGINAL",
    "badge-1": "2023",
    "badge-2": "дубляж",
    "badge-3": "122 минути",
    "badge-4": "1080p",
    "hero-desc": "После событий первой части Тайлер Рейк чудом остаётся в живых и получает новое задание. На этот раз ему предстоит освободить семью, оказавшуюся в плену у жестокого грузинского криминального клана. Операция быстро превращается в масштабную войну, где Тайлера ждут смертельно опасные противники, погони и ожесточённые перестрелки.",
    "imdb-rating": "X",
    "genre-1": "БОЕВИК"
  },
  "videoUrl": "",
  "siteName": "Видеоархив 2023",
  "siteTagline": "ОПЕРАЦИЯ ПО СПАСЕНИЮ 2",
  "footerText": "©  ОПЕРАЦИЯ ПО СПАСЕНИЮ 2 • 2023 • NETFLIX",
  "heroBg": {
    "type": "",
    "value": ""
  },
  "bgPosition": {
    "x": 50,
    "y": 0,
    "scale": 1
  },
  "colors": {
    "title": "",
    "accentText": "",
    "btn": "",
    "shape": "",
    "bgPrimary": "",
    "bgSecondary": ""
  }
}