{
  "title": "Основание",
  "poster": "",
  "fields": {
    "hero-title": "Основание",
    "hero-eyebrow": "| Apple tv+",
    "badge-1": "2021",
    "badge-2": "Дубляж",
    "badge-3": "10 серий",
    "badge-4": "1080p"
  },
  "videoUrl": "",
  "siteName": "Видеоархив ",
  "siteTagline": "Основание 1 сезон",
  "footerText": "© Видеоархив",
  "heroBg": {
    "type": "",
    "value": ""
  },
  "bgPosition": {
    "x": 50,
    "y": 0,
    "scale": 1
  },
  "colors": {
    "title": "",
    "accentText": "",
    "btn": "",
    "shape": "",
    "bgPrimary": "",
    "bgSecondary": ""
  }
}